asyncsomecomfort/__init__.py
asyncsomecomfort/client.py
asyncsomecomfort/device.py
asyncsomecomfort/event_emitter.py
asyncsomecomfort/exceptions.py
asyncsomecomfort/location.py
asyncsomecomfort/session.py
async_somecomfort-1.0.0.dist-info/LICENSE
async_somecomfort-1.0.0.dist-info/METADATA
async_somecomfort-1.0.0.dist-info/WHEEL
async_somecomfort-1.0.0.dist-info/top_level.txt
async_somecomfort-1.0.0.dist-info/RECORD
