Metadata-Version: 2.1
Name: async-somecomfort
Version: 1.0.0
Summary: Python client for interacting with Honeywell Total Connect Comfort (TCC) API
Home-page: https://github.com/yourusername/async-somecomfort
Author: Your Name
Author-email: your.email@example.com
Classifier: Programming Language :: Python :: 3
Classifier: License :: OSI Approved :: MIT License
Classifier: Operating System :: OS Independent
Requires-Python: >=3.6
License-File: LICENSE
Requires-Dist: aiohttp >=3.7.4
